aiorethink/__init__.py
aiorethink/db.py
aiorethink/document.py
aiorethink/errors.py
aiorethink/field.py
aiorethink/registry.py
aiorethink/values_and_valuetypes/__init__.py
aiorethink/values_and_valuetypes/base_types.py
aiorethink/values_and_valuetypes/field_container.py
aiorethink/values_and_valuetypes/lazy.py
aiorethink/values_and_valuetypes/reference.py
aiorethink/values_and_valuetypes/simple_containers.py
aiorethink/values_and_valuetypes/simple_types.py
aiorethink-0.2.1.dist-info/DESCRIPTION.rst
aiorethink-0.2.1.dist-info/METADATA
aiorethink-0.2.1.dist-info/RECORD
aiorethink-0.2.1.dist-info/WHEEL
aiorethink-0.2.1.dist-info/metadata.json
aiorethink-0.2.1.dist-info/top_level.txt
