Metadata-Version: 2.0
Name: aiorethink
Version: 0.2.1
Summary: Asynchronous asyncio compatible ODM for RethinkDB
Home-page: https://github.com/lars-tiede/aiorethink
Author: Lars Tiede
Author-email: lars.tiede@gmail.com
License: MIT
Platform: UNKNOWN
Classifier: Development Status :: 2 - Pre-Alpha
Classifier: Environment :: Web Environment
Classifier: Intended Audience :: Developers
Classifier: License :: OSI Approved :: MIT License
Classifier: Operating System :: OS Independent
Classifier: Programming Language :: Python :: 3 :: Only
Classifier: Programming Language :: Python :: 3.5
Classifier: Topic :: Database
Classifier: Topic :: Internet :: WWW/HTTP :: Dynamic Content
Requires-Dist: inflection
Requires-Dist: rethinkdb
